PyroArgs/__init__.py
PyroArgs/parser.py
PyroArgs/pyroargs.py
PyroArgs/errors/ArgumentTypeError.py
PyroArgs/errors/ArgumentsError.py
PyroArgs/errors/CommandError.py
PyroArgs/errors/CommandPermissionError.py
PyroArgs/errors/MissingArgumentError.py
PyroArgs/errors/__init__.py
PyroArgs/types/__init__.py
PyroArgs/types/command.py
PyroArgs/types/commandRegistry.py
PyroArgs/types/events.py
PyroArgs/types/logger.py
PyroArgs/types/message.py
PyroArgs/utils/DataHolder.py
PyroArgs/utils/__init__.py
pyroargs-1.4.dist-info/licenses/LICENSE
pyroargs-1.4.dist-info/METADATA
pyroargs-1.4.dist-info/WHEEL
pyroargs-1.4.dist-info/top_level.txt
pyroargs-1.4.dist-info/RECORD
