Metadata-Version: 2.4
Name: PyroArgs
Version: 1.4
Summary: Удобная обработка аргументов команд для Pyrogram
Home-page: https://github.com/vo0ov/TG-UserBot
Author: vo0ov
Author-email: artgr123@yandex.ru
Classifier: Development Status :: 3 - Alpha
Classifier: Intended Audience :: Developers
Classifier: Programming Language :: Python :: 3
Classifier: License :: OSI Approved :: MIT License
Classifier: Operating System :: OS Independent
Requires-Python: >=3.7
License-File: LICENSE
Requires-Dist: pyrogram>=2.0.0
Provides-Extra: all
Requires-Dist: TgCrypto>=1.2.2; extra == "all"
Provides-Extra: crypto
Requires-Dist: TgCrypto>=1.2.2; extra == "crypto"
Dynamic: author
Dynamic: author-email
Dynamic: classifier
Dynamic: description
Dynamic: description-content-type
Dynamic: home-page
Dynamic: license-file
Dynamic: provides-extra
Dynamic: requires-dist
Dynamic: requires-python
Dynamic: summary
